temporaldata/__init__.py
temporaldata/concat.py
temporaldata/temporaldata.py
temporaldata-0.1.2.dist-info/LICENSE
temporaldata-0.1.2.dist-info/METADATA
temporaldata-0.1.2.dist-info/WHEEL
temporaldata-0.1.2.dist-info/top_level.txt
temporaldata-0.1.2.dist-info/RECORD
