Metadata-Version: 2.2
Name: temporaldata
Version: 0.1.2
Summary: A utility package for complex temporal data manipulation
Author-email: Mehdi Azabou <mehdiazabou@gmail.com>
License: MIT
Project-URL: Homepage, https://github.com/neuro-galaxy/temporaldata
Project-URL: Issues, https://github.com/neuro-galaxy/temporaldata/issues
Project-URL: Documentation, https://temporaldata.readthedocs.io/en/latest/
Classifier: Programming Language :: Python :: 3
Classifier: License :: OSI Approved :: MIT License
Classifier: Operating System :: OS Independent
Requires-Python: >=3.8
License-File: LICENSE
Requires-Dist: setuptools>=60.0.0
Requires-Dist: numpy>=1.14.0
Requires-Dist: pandas>=1.0.0
Requires-Dist: h5py>=3.0.0
Provides-Extra: dev
Requires-Dist: pytest; extra == "dev"
Requires-Dist: black==24.2.0; extra == "dev"
Requires-Dist: pre-commit>=3.5.0; extra == "dev"
Requires-Dist: flake8; extra == "dev"
